FullMatrix/FullMatrix.py
FullMatrix/__init__.py
FullMatrix/__main__.py
FullMatrix/_version.py
FullMatrix-1.0.5.dist-info/LICENSE
FullMatrix-1.0.5.dist-info/METADATA
FullMatrix-1.0.5.dist-info/WHEEL
FullMatrix-1.0.5.dist-info/entry_points.txt
FullMatrix-1.0.5.dist-info/top_level.txt
FullMatrix-1.0.5.dist-info/RECORD
