Metadata-Version: 2.1
Name: FullMatrix
Version: 1.0.5
Summary: full matrix coordinates
Home-page: https://pypi.org/project/FullMatrix/
Author: Benxia Hu
Author-email: hubenxia@gmail.com
License: UNKNOWN
Platform: UNKNOWN
Classifier: Programming Language :: Python :: 3
Classifier: License :: OSI Approved :: MIT License
Classifier: Operating System :: OS Independent
Requires-Python: >=3.6
Requires-Dist: numpy
Requires-Dist: pandas
Requires-Dist: argparse
